Plutupus/__init__.py
Plutupus/Mocha/Mocha.py
Plutupus/Mocha/__init__.py
Plutupus/TxBody/TxBody.py
Plutupus/TxBody/__init__.py
Plutupus/Types/Address.py
Plutupus/Types/AssetClass.py
Plutupus/Types/AssocMap.py
Plutupus/Types/BuiltinByteString.py
Plutupus/Types/CurrencySymbol.py
Plutupus/Types/Integer.py
Plutupus/Types/PList.py
Plutupus/Types/POSIXTime.py
Plutupus/Types/PTuple.py
Plutupus/Types/PubKeyHash.py
Plutupus/Types/TokenName.py
Plutupus/Types/TxOutRef.py
Plutupus/Types/Value.py
Plutupus/Types/__init__.py
Plutupus/Types/abstract.py
Plutupus/Types/base_types.py
Plutupus/Types/utils.py
TxBody/TxBody.py
TxBody/__init__.py
Types/Address.py
Types/AssetClass.py
Types/AssocMap.py
Types/BuiltinByteString.py
Types/CurrencySymbol.py
Types/Integer.py
Types/PList.py
Types/POSIXTime.py
Types/PTuple.py
Types/PubKeyHash.py
Types/TokenName.py
Types/TxOutRef.py
Types/Value.py
Types/__init__.py
Types/utils.py
tests/__init__.py
tests/test_types.py
tests/types/__init__.py
tests/types/test_abstract.py
tests/types/test_address.py
tests/types/test_base_types.py
plutupus-0.4.0.dist-info/LICENSE
plutupus-0.4.0.dist-info/METADATA
plutupus-0.4.0.dist-info/WHEEL
plutupus-0.4.0.dist-info/top_level.txt
plutupus-0.4.0.dist-info/RECORD
