Metadata-Version: 2.1
Name: plutupus
Version: 0.4.0
Summary: A utility plutus utility package
Home-page: https://github.com/athena-labz/plutupus
Author: Mateus Santos
Author-email: santos.mateus@protonmail.com
License: UNKNOWN
Platform: UNKNOWN
Classifier: Programming Language :: Python :: 3
Classifier: Development Status :: 3 - Alpha
Classifier: License :: OSI Approved :: MIT License
Classifier: Operating System :: OS Independent
License-File: LICENSE
